gdb_mcp/__init__.py
gdb_mcp/gdb_session.py
gdb_mcp/installer.py
gdb_mcp/server.py
gdb_mcp-1.0.1.dist-info/METADATA
gdb_mcp-1.0.1.dist-info/WHEEL
gdb_mcp-1.0.1.dist-info/entry_points.txt
gdb_mcp-1.0.1.dist-info/top_level.txt
gdb_mcp-1.0.1.dist-info/RECORD
